pyesys/__init__.py
pyesys/event.py
pyesys/handler.py
pyesys/prop.py
pyesys-0.2.1.dist-info/licenses/LICENSE
pyesys-0.2.1.dist-info/WHEEL
pyesys-0.2.1.dist-info/METADATA
pyesys-0.2.1.dist-info/RECORD
