Metadata-Version: 2.4
Name: pyesys
Version: 0.2.1
Summary: A Python-native event system that provides thread-safe, type-safe event handling with first-class async support. Designed for real-world applications requiring robust concurrency, simulation, or external control mechanisms.
Keywords: event,pubsub,async,python
Author-email: Goodwill Mzumala <fisothemes@gmail.com>
Requires-Python: >=3.12
License-Expression: MIT
Classifier: Programming Language :: Python :: 3
Classifier: Programming Language :: Python :: 3.12
Classifier: Operating System :: OS Independent
License-File: LICENSE
Requires-Dist: sphinx>=8.2.3 ; extra == "ci-doc"
Requires-Dist: sphinx-rtd-theme>=3.0.2 ; extra == "ci-doc"
Requires-Dist: pytest>=8.3.5 ; extra == "ci-test"
Requires-Dist: pytest-asyncio>=1.0.0 ; extra == "ci-test"
Requires-Dist: pytest>=8.3.5 ; extra == "dev"
Requires-Dist: pytest-asyncio>=1.0.0 ; extra == "dev"
Requires-Dist: black>=25.1.0 ; extra == "dev"
Requires-Dist: sphinx>=8.2.3 ; extra == "dev"
Requires-Dist: sphinx-rtd-theme>=3.0.2 ; extra == "dev"
Project-URL: Documentation, https://fisothemes.github.io/pyesys/
Project-URL: Issues, https://github.com/fisothemes/pyesys/issues
Project-URL: Source, https://github.com/fisothemes/pyesys
Provides-Extra: ci-doc
Provides-Extra: ci-test
Provides-Extra: dev
